README.txt
setup.py
barpy/__init__.py
barpy/barcode/__init__.py
barpy/barcode/base.py
barpy/barcode/code_128.py
barpy/barcode/ean_13.py
barpy/barcode/gs1_128.py
barpy/barcode/qr_code.py
barpy/outputter/__init__.py
barpy/outputter/ascii_outputter.py
barpy/outputter/base.py
barpy/outputter/html_outputter.py
barpy/outputter/png_outputter.py
cfc_barpy.egg-info/PKG-INFO
cfc_barpy.egg-info/SOURCES.txt
cfc_barpy.egg-info/dependency_links.txt
cfc_barpy.egg-info/requires.txt
cfc_barpy.egg-info/top_level.txt